Workbook

Sheet Dashboard
A1: GUARDIAN / EXECUTION SCORECARD
A2: Pilot: Oct 19 – Nov 29, 2026 • Enter actual evidence in the supporting sheets; targets are hypotheses, not forecasts.
A4: KPI | B4: Actual | C4: G6 target | D4: Gate result | E4: Source | F4: Interpretation
A5: Qualified interviews | B5: =COUNTIF('Interview Log'!D5:D40,"Yes") | C5: 8 | D5: =IF(B5>=C5,"PASS","BELOW") | E5: Interview Log | F5: Developers using 2+ coding sessions recently
A6: Recent pain validated | B6: =COUNTIFS('Interview Log'!D5:D40,"Yes",'Interview Log'!E5:E40,"Yes") | C6: 5 | D6: =IF(B6>=C6,"PASS","BELOW") | E6: Interview Log | F6: Specific coordination incident within 30 days
A7: Alpha testers completed | B7: =COUNTIF('Alpha Testers'!E5:E30,"Yes") | C7: 4 | D7: =IF(B7>=C7,"PASS","BELOW") | E7: Alpha Testers | F7: 4 of 5 target testers finish guided workflow
A8: Verified unique installs | B8: =SUM('Weekly Metrics'!F5:F10) | C8: 50 | D8: =IF(B8>=C8,"PASS","BELOW") | E8: Weekly Metrics | F8: Unique first-time installs, not download count
A9: Activated users | B9: =SUM('Weekly Metrics'!G5:G10) | C9: 15 | D9: =IF(B9>=C9,"PASS","BELOW") | E9: Weekly Metrics | F9: Generated a risk report successfully
A10: Repeat users | B10: =SUM('Weekly Metrics'!H5:H10) | C10: 8 | D10: =IF(B10>=C10,"PASS","BELOW") | E10: Weekly Metrics | F10: Used on a separate day/session; count once
A11: Paying customers | B11: =SUM('Weekly Metrics'!I5:I10) | C11: 3 | D11: =IF(B11>=C11,"PASS","BELOW") | E11: Weekly Metrics | F11: Genuine customers; refunds excluded
A12: Critical safety incidents | B12: =SUM('Weekly Metrics'!M5:M10) | C12: 0 | D12: =IF(COUNT('Weekly Metrics'!M5:M10)=0,"NOT REPORTED",IF(B12=0,"PASS","FAIL")) | E12: Weekly Metrics | F12: Zero tolerated
A13: Activation rate | B13: =IFERROR(B9/B8,0) | C13: 0.3 | D13: =IF(B13>=C13,"PASS","BELOW") | E13: Calculated | F13: Target heuristic: 30%+ of installs
A14: Repeat rate | B14: =IFERROR(B10/B9,0) | C14: 0.5 | D14: =IF(B14>=C14,"PASS","BELOW") | E14: Calculated | F14: Target heuristic: 50%+ of activated
A15: Paid conversion of activated | B15: =IFERROR(B11/B9,0) | C15: 0.2 | D15: =IF(B15>=C15,"PASS","BELOW") | E15: Calculated | F15: Target heuristic: 20%+ of activated
A16: Gross revenue (USD) | B16: =SUM('Weekly Metrics'!J5:J10) | E16: Weekly Metrics | F16: Collected gross; not profit
A17: Net receipts (USD) | B17: =B16-SUM('Weekly Metrics'!K5:K10)-SUM('Weekly Metrics'!L5:L10) | E17: Weekly Metrics | F17: Gross less refunds and payment fees
A19: READOUT / HOW TO USE
A20: 1. Set weekly actuals and evidence; never populate metrics with aspirational numbers.
A21: 2. Update milestone gate status only after collecting evidence and reviewing pass criteria.
A22: 3. Interview results are counted from Interview Log; alpha completion from Alpha Testers.
A23: 4. Distinct user counts must be deduplicated across weeks; opt-in/self-reported is acceptable.
A24: 5. Safety incident >0 blocks public rollout regardless of other KPIs.
A25: 6. At G6 choose Scale / Iterate / Pivot / Stop in Decision Log.

Sheet Milestones
A1: MILESTONE GATES
A2: A gate cannot pass simply because its tasks are marked complete. Attach evidence and record the founder's decision.
A4: Gate | B4: Week / dates | C4: Delivery | D4: Evidence-based exit criteria | E4: Owner | F4: Status | G4: Evidence URL / path | H4: Decision / notes
A5: G1 | B5: Oct 19–25 | C5: Research and charter | D5: >=10 competitors; >=8 interviews; >=5 describe recent pain; PRD frozen | E5: Founder | F5: Done | G5: docs/RESEARCH_G1.md | H5: Closed 2026-10-17 by desk research (10 sourced pain points, 20-tool matrix). Interview round dropped by founder on 2026-10-20; H1 accepted on desk research + founder incidents. GO to G2 with wedge = task ownership + preflight overlap.
A6: G2 | B6: Oct 26–Nov 1 | C6: Local prototype | D6: Inspection + task claims + risk/handoff; >=20 fixtures; no surprise writes | E6: Engineering / founder review | F6: Done | G6: docs/SAFETY_AUDIT.md; tests/ (19 CLI + 16 mod + hook); CI green; demo/scenarios.sh; tag v0.1.0 | H6: Closed 2026-10-20, ahead of the Oct 26–Nov 1 window. All five deliverables with evidence. Demo recordings (G2-09) prepared via demo/scenarios.sh; the clips themselves are the founder's. Windows support added 2026-10-23 (CLI 0.2.1, mod 0.17.0), CI green on ubuntu+macos+windows at 7007167.
A7: G3 | B7: Nov 2–8 | C7: Private alpha | D7: >=5 testers; >=4 completed guided flow; 0 critical incidents | E7: Founder | F7: Ready — awaiting testers | G7: docs/ALPHA_GUIDE.md; docs/ALPHA_OUTREACH.md | H7: Everything a tester needs exists. Exit needs 5 real testers observed; cannot be closed without them.
A8: G4 | B8: Nov 9–15 | C8: Public free beta | D8: Tagged release, guides, privacy, demo; 0 known P0/P1 issues | E8: Founder | F8: Ready — awaiting launch | G8: CHANGELOG.md; docs/PRIVACY.md; docs/RELEASE_CHECKLIST.md; .github/ISSUE_TEMPLATE; release v0.1.0 | H8: Public repo, tagged release, docs, privacy, issue templates done. Exit needs the directory submission, demo clips posted, and ≥50 verified installs measured.
A9: G5 | B9: Nov 16–22 | C9: Paid-value test | D9: Checkout/fulfillment tested; clear differentiation; real buyer feedback | E9: Founder | F9: Ready — awaiting build + checkout | G9: docs/PRICING.md | H9: Free/Pro boundary, two price messages, checkout/fulfilment/refund plan written. Exit needs Pro features behind a license, a live checkout, and real buyers.
A10: G6 | B10: Nov 23–29 | C10: Continue/pivot decision | D10: >=50 installs; >=15 activated; >=8 repeat; >=3 paying; safe operation | E10: Founder | F10: Template ready | G10: docs/DECISION_MEMO.md | H10: Memo template with thresholds and formulas. Exit is the dated decision on 2026-11-29 with frozen metrics.

Sheet Backlog
A1: DELIVERY BACKLOG
A2: Update owner, status, evidence, and blockers. 'Done' requires acceptance evidence—not only an AI claim.
A4: Task ID | B4: Gate | C4: Priority | D4: Deliverable / ticket | E4: Owner | F4: Due | G4: Status | H4: Acceptance / done condition | I4: Evidence link | J4: Blocker / notes
A5: G1-01 | B5: G1 | C5: P0 | D5: Competitive matrix: >=10 tools | E5: Founder | F5: 2026-10-22 | G5: Done | H5: Features, price, links, gaps verified | I5: docs/RESEARCH_G1.md §2 | J5: 20 tools, A–D columns verified/unverified
A6: G1-02 | B6: G1 | C6: P0 | D6: Recruit 8–10 qualified interviewees | E6: Founder | F6: 2026-10-23 | G6: Dropped | H6: Candidates used 2+ agent sessions in last month | I6: docs/MASTER_PLAN.md §15 | J6: Founder decision 2026-10-20: desk research + own incidents replace interviews
A7: G1-03 | B7: G1 | C7: P0 | D7: Conduct problem interviews | E7: Founder | F7: 2026-10-25 | G7: Dropped | H7: >=8 notes; >=5 recent incidents for H1 | I7: docs/MASTER_PLAN.md §15 | J7: see G1-02
A8: G1-04 | B8: G1 | C8: P0 | D8: PRD + go/no-go decision | E8: Founder | F8: 2026-10-25 | G8: Done | H8: Scope and unmet value wedge written | I8: docs/RESEARCH_G1.md §5; MASTER_PLAN §15 | J8: GO to G2; wedge re-scoped
A9: G2-01 | B9: G2 | C9: P0 | D9: CLI inspect + repo/worktree model | E9: Engineering | F9: 2026-10-28 | G9: Done | H9: Works offline; read-only; documented output | I9: src/commands/inspect.ts; tests/cli.test.ts | J9: worktrees, locks, in-flight ops, task↔worktree map
A10: G2-02 | B10: G2 | C10: P0 | D10: Task manifest + explicit claims | E10: Engineering | F10: 2026-10-29 | G10: Done | H10: Never silently writes; validates path input | I10: src/commands/task.ts; plugins/session-agents/hooks/tasks.ts | J10: shared .guardian/tasks.json; mod holds edits and asks the user
A11: G2-03 | B11: G2 | C11: P0 | D11: Risk report overlapping tasks | E11: Engineering | F11: 2026-10-30 | G11: Done | H11: Catches overlap fixtures with evidence | I11: src/lib/analyze.ts; tests/cli.test.ts | J11: 10 finding types with fixes; suggested merge order
A12: G2-04 | B12: G2 | C12: P0 | D12: Evidence-based handoff report | E12: Engineering | F12: 2026-10-30 | G12: Done | H12: Unknown test result says 'Not verified' | I12: src/commands/handoff.ts | J12: verified / supplied-not-verified / not verified; tree fingerprint
A13: G2-05 | B13: G2 | C13: P0 | D13: 20+ fixtures and safety audit | E13: Engineering / founder | F13: 2026-11-01 | G13: Done | H13: All critical fixtures green; no destructive commands | I13: docs/SAFETY_AUDIT.md; tests/ | J13: 19 CLI + 16 mod + hook tests; audit row by row
A14: G3-01 | B14: G3 | C14: P0 | D14: Alpha onboarding and demo guide | E14: Founder | F14: 2026-11-03 | G14: Done | H14: New user can run workflow from clean clone | I14: docs/ALPHA_GUIDE.md
A15: G3-02 | B15: G3 | C15: P0 | D15: Recruit 5 alpha testers | E15: Founder | F15: 2026-11-04 | G15: Ready | H15: Five distinct qualified volunteers | I15: docs/ALPHA_OUTREACH.md | J15: targets + message drafted; sending is the founder's
A16: G3-03 | B16: G3 | C16: P0 | D16: Observe 5 full workflows | E16: Founder | F16: 2026-11-08 | G16: Not Started | H16: >=4 finish, feedback recorded per tester
A17: G4-01 | B17: G4 | C17: P0 | D17: Public beta release checklist | E17: Engineering / founder | F17: 2026-11-11 | G17: Done | H17: License, docs, privacy, changelog, smoke test | I17: docs/RELEASE_CHECKLIST.md; release v0.1.0
A18: G4-02 | B18: G4 | C18: P1 | D18: 2 short product demo videos | E18: Founder | F18: 2026-11-13 | G18: Done (terminal clips) | H18: Screens include overlap and handoff scenarios | I18: demo/recordings/ | J18: script ready; recordings owed
A19: G4-03 | B19: G4 | C19: P1 | D19: Launch distribution experiments | E19: Founder | F19: 2026-11-15 | G19: Ready | H19: Channels logged; follows community rules | I19: docs/RESEARCH_G1.md §4 channel list | J19: directory submission + Reddit/HN/X posts are the founder's
A20: G5-01 | B20: G5 | C20: P0 | D20: Paid value and pricing experiment | E20: Founder | F20: 2026-11-18 | G20: In Progress | H20: Distinct Pro benefit; non-leading buyer feedback | I20: workspace-guardian-pro@400c0cb; src/lib/license.ts; tests/pro.test.ts | J20: Pro 0.1.0 built + verified with a signed key 2026-10-23; checkout page and price messages still owed
A21: G5-02 | B21: G5 | C21: P0 | D21: Checkout, fulfillment, support test | E21: Founder | F21: 2026-11-20 | G21: Ready — founder setup | H21: Successful test order, delivery and policy | I21: docs/CHECKOUT_LEMONSQUEEZY.md; workspace-guardian-pro scripts/pack.sh, scripts/fulfil.ts | J21: engineering done 2026-10-23; store creation, test purchase and refund are the founder's
A22: G6-01 | B22: G6 | C22: P0 | D22: Cohort/funnel and safety review | E22: Founder | F22: 2026-11-28 | G22: Not Started | H22: Metrics deduplicated, evidence reviewed
A23: G6-02 | B23: G6 | C23: P0 | D23: Scale/iterate/pivot/stop memo | E23: Founder | F23: 2026-11-29 | G23: Template | H23: Decision, reasons, 30-day next actions | I23: docs/DECISION_MEMO.md
A24: G2-06 | B24: G2 | C24: P0 | D24: Push to GitHub, CI green on ubuntu+macos, replace <owner>/<repo> | E24: Founder / engineering | F24: 2026-10-24 | G24: Done | H24: .github/workflows/ci.yml passes on both OSes | I24: https://github.com/d10or/workspace-guardian/actions/runs/39390316230 | J24: 3 jobs green on first push
A25: G2-07 | B25: G2 | C25: P0 | D25: Choose license (R7) and add LICENSE | E25: Founder | F25: 2026-10-24 | G25: Done | H25: LICENSE file; package.json license updated | I25: LICENSE; package.json | J25: MIT
A26: G2-08 | B26: G2 | C26: P1 | D26: Mod: per-session files for notes/pins/messages; version-match test | E26: Engineering | F26: 2026-10-30 | G26: Done | H26: claude plugin test green | I26: plugins/session-agents v0.15.0; .github/workflows/ci.yml | J26: messages per session, timer guard, version check in CI
A27: G2-09 | B27: G2 | C27: P1 | D27: Record demo: clean repo, risky overlap, safe handoff | E27: Founder | F27: 2026-11-01 | G27: Done (terminal clips) | H27: 2 short recordings | I27: demo/recordings/*.gif; README "See it" | J27: 3 terminal clips recorded by Claude, approved by founder 2026-10-20; the in-Claude-Code Allow/Deny clip is still the founder's
A28: G4-04 | B28: G4 | C28: P2 | D28: Free SKILL.md wrapper for the CLI listed on Agensi.io (discovery for Cursor/Codex users) | E28: Engineering / founder | F28: 2026-11-20 | G28: Not Started | H28: skill lists, points at repo + store; zero Pro content | J28: after launch data exists; never Pro

Sheet Weekly Metrics
A1: WEEKLY METRICS
A2: Editable cells start at B5. Enter NEW unique counts per week; do not double-count returning users.
A4: Week ending | B4: Qualified interviews (info) | C4: Recent pain (info) | D4: Alpha started (info) | E4: Alpha completed (info) | F4: New unique installs | G4: New activated | H4: New users 2nd use | I4: New paying customers | J4: Gross USD | K4: Refunds USD | L4: Fees USD | M4: Critical incidents | N4: Evidence / channel notes
A5: 2026-10-25
A6: 2026-11-01
A7: 2026-11-08
A8: 2026-11-15
A9: 2026-11-22
A10: 2026-11-29
A13: WARNING: Blank means not reported. A zero means reviewed and confirmed zero. Entries in B–E are informational; dashboard uses Interview Log and Alpha Testers.

Sheet Interview Log
A1: CUSTOMER DISCOVERY LOG
A2: Use anonymized interview IDs. Do not store full names, personal emails, or proprietary code here.
A4: Interview ID | B4: Date | C4: Channel / persona | D4: Qualified? | E4: Specific recent incident? | F4: Incident / time lost (sanitized) | G4: Current workaround | H4: Top unmet pain | I4: Would pay after demo? | J4: Evidence / notes

Sheet Alpha Testers
A1: ALPHA TESTER LOG
A2: One tester per row. Completion means independently finished inspect → claim → check → handoff.
A4: Tester ID | B4: Date | C4: Qualified? | D4: Completed scenario? (notes) | E4: Completed? | F4: Usability issue | G4: Would use again? | H4: Safety issue? | I4: Evidence / follow-up

Sheet Risk Register
A1: RISK REGISTER
A2: Owner reviews risks each Monday; every safety incident blocks release until resolved.
A4: Risk ID | B4: Risk | C4: Likelihood | D4: Impact | E4: Mitigation | F4: Trigger / evidence | G4: Owner | H4: Status
A5: R1 | B5: Existing tools already solve buyer pain | C5: High | D5: High | E5: Validate unmet gap with real users | F5: <5 verified pain interviewees | G5: Founder | H5: Open
A6: R2 | B6: Unexplainable false positives | C6: Medium | D6: High | E6: Explain warnings; fixtures and label confidence | F6: >20% false warnings on labeled alpha fixtures | G6: Engineering | H6: Open
A7: R3 | B7: Missed overlap gives false safety | C7: Medium | D7: High | E7: Advisory-only; edge cases; no safety guarantee | F7: Known overlapping fixture not detected | G7: Engineering | H7: Open
A8: R4 | B8: Secret leakage / destructive repo ops | C8: Low | D8: Critical | E8: Offline default; explicit writes; secure process execution | F8: Any unapproved repo write or egress | G8: Founder | H8: Open
A9: R5 | B9: No reason to pay over free tools | C9: High | D9: Medium | E9: Test differentiated paid feature and support | F9: No credible paid signals after qualified demos | G9: Founder | H9: Open
A10: R6 | B10: Too much engineering before demand proof | C10: Medium | D10: High | E10: G1 gate first; cap P0 scope | F10: UI/backend built before validated gap | G10: Founder | H10: Open
A11: R7 | B11: Company/third-party license conflicts | C11: Medium | D11: High | E11: Synthetic examples; provenance review | F11: Unapproved reuse of proprietary material | G11: Founder | H11: Mitigated: PolyForm Shield on public repo; Pro private; provenance notes record the MIT window (0 clones)
A12: R8 | B12: Radar or Anthropic absorbs the handoff / merge-readiness layer | C12: Medium | D12: High | E12: Own the preflight ownership layer first; integrate with Radar rather than compete if it gains traction | F12: Radar stars/releases; Anthropic changelog (worktree + TaskCompleted hooks) | G12: Founder | H12: Open

Sheet Decision Log
A1: DECISION LOG
A2: Capture every gate result, product pivot, scope or target change with rationale and evidence.
A4: Decision ID | B4: Date | C4: Gate | D4: Decision | E4: Evidence & rationale | F4: Decision owner | G4: Next action / due
A5: D1 | B5: 2026-10-17 | C5: G1 | D5: GO to G2; wedge = task-level path ownership + preflight overlap (P3, P1, P7); handoff/merge-readiness fast-follow | E5: Desk research: A+B empty across 20 tools; Radar (Oct 2026) already ships test-evidence gate. docs/RESEARCH_G1.md | F5: Founder | G5: Start G2 from session-agents mod
A6: D2 | B6: 2026-10-20 | C6: G1 | D6: Drop the interview round; accept H1 on desk research + founder incidents | E6: Sourced evidence (41.7% cross-agent conflict rate; 35–69% unverified test claims) and the mod itself was built from founder incidents | F6: Founder | G6: Feedback from G3 alpha testers
A7: D3 | B7: 2026-10-20 | C7: G5 | D7: Pricing: low price, volume ($5–$12 one-time or a few $/month); test two points at G5 | E7: Comparables: SessionWatcher $6.99/$14.99; Vibe Kanban failed at $30/user | F7: Founder | G7: Define Pro boundary before G5
A8: D4 | B8: 2026-10-20 | C8: G2 | D8: Adopt session-agents mod as the interactive surface; CLI and mod share .guardian/tasks.json | E8: docs/MOD_REVIEW.md; live ownership hold observed 2026-10-20 | F8: Founder | G8: G2-06..09
A9: D5 | B9: 2026-10-20 | C9: G2 | D9: G2 closed with evidence; G3–G6 artifacts prepared; G3–G6 exits stay open until real testers, installs and buyers exist | E9: docs/SAFETY_AUDIT.md, CI, release v0.1.0; MASTER_PLAN §5 pass criteria need external evidence that cannot be produced internally | F9: Founder | G9: Send alpha outreach (G3-02); record demo clips (G2-09)
A10: D6 | B10: 2026-10-20 | C10: G4/G5 | D10: Relicense public repo MIT → PolyForm Shield 1.0.0; paid features in private repo workspace-guardian-pro; drop awesome-claude-code channel | E10: Founder requirement: nobody may clone the project and offer it as their own. GitHub traffic at change: 0 clones, 0 forks, 0 stars. Shield allows use at work, forbids competing products. | F10: Founder | G10: Create pro repo skeleton + license-key design (done 2026-10-20)
A11: D7 | B11: 2026-10-23 | C11: G5 | D11: Checkout provider: Lemon Squeezy; manual key fulfilment during pilot; webhook signer deferred | E11: Merchant of record (tax), file delivery, two price variants on one product; 3-buyer pass mark makes manual fulfilment fine | F11: Founder | G11: Set up store per docs/CHECKOUT_LEMONSQUEEZY.md; test purchase + refund
A12: D8 | B12: 2026-10-23 | C12: G5 | D12: Founding price: Pro $1/month for first 30 days or 100 buyers, grandfathered; free core stays free and public | E12: Paid users are the feedback cohort; no marketplace can sell a Claude Code mod; directory lists free plugins only; Lemon Squeezy nets ~$0.45/$1 | F12: Founder | G12: Create store with variant F; launch posts carry the founding line
A13: D9 | B13: 2026-10-23 | C13: G4/G5 | D13: Sell only via Lemon Squeezy; list a free SKILL.md wrapper on Agensi.io after launch (discovery for Cursor/Codex users), never Pro | E13: Agensi sells SKILL.md files only, via its own MCP connector, 30% fee; numbers self-reported; our Pro is a package + key | F13: Founder | G13: Add backlog G4-04 after launch

Sheet Competitors
A1: COMPETITOR MATRIX
A2: Initial evidence-based seed list. Expand to 10+ verified direct/adjacent competitors during G1.
A4: Product | B4: Type | C4: Native parallel sessions | D4: Overlap preflight | E4: Evidence handoff | F4: Pricing / license | G4: Evidence link | H4: Gap to verify
A5: Claude Code native | B5: First-party CLI | C5: Yes (worktrees, teams) | D5: Research | E5: Research | F5: Depends on Claude plan | G5: https://support.claude.com/en/articles/14554000-claude-code-power-user-tips | H5: How independent sessions share task claims
A6: Conductor | B6: GUI workspace manager | C6: Yes | D6: Research | E6: Workspace notes + checks | F6: Verify current plan | G6: https://www.conductor.build/docs/guides/parallel-agents/run-multiple-claude-code-sessions | H6: Pre-branch task scope vs post-change diff
A7: Claude Squad | B7: TUI session manager | C7: Yes (tmux/worktrees) | D7: Research | E7: Research | F7: AGPL-3.0 repo license | G7: https://github.com/smtg-ai/claude-squad | H7: Structured collision prevention vs session status
A8: Vibe Kanban | B8: Agent Kanban/workspaces | C8: Yes | D8: Research | E8: Diff review | F8: Project sunsetting | G8: https://vibekanban.com/ | H8: Community fork, maintenance and feature overlap
A9: worktrunk (wt) | B9: Worktree CLI for agents | C9: Yes (worktrees) | D9: No | E9: No (merge-tree conflict flag only) | F9: Free, MIT/Apache; v0.80 Sep 2026 | G9: https://worktrunk.dev/list/ | H9: merges itself; Guardian report as pre-merge hook
A10: Radar | B10: Local merge gate + MCP | C10: n/a | D10: Partial (post-hoc drift) | E10: Yes: PASS/FAIL/NOT VERIFIED, Radar-Verified trailer | F10: Free, MIT; created 2026-10-09, 2 stars | G10: https://github.com/Jake-Network/radar | H10: closest on C/D; no path ownership
A11: Superset (YC) | B11: Agent IDE | C11: Yes | D11: No (states worktrees do not prevent conflicts) | E11: No | F11: Free; Pro $20/user/mo | G11: https://superset.sh/pricing | H11: needs-rebase marker only
A12: Crystal → Nimbalyst | B12: Desktop session manager | C12: Yes | D12: No | E12: No | F12: MIT; Teams $20/user | G12: https://nimbalyst.com | H12: isolation only
A13: ccmanager | B13: TUI session manager | C13: Yes | D13: No | E13: No | F13: Free, MIT; v4.4.8 Oct 2026 | G13: https://github.com/kbwo/ccmanager | H13: copies session data between worktrees
A14: agent-of-empires | B14: Rust tmux manager | C14: Yes | D14: No | E14: No | F14: Free, MIT; v1.20 Oct 2026 | G14: https://github.com/agent-of-empires/agent-of-empires | H14: diff view only

Sheet Definitions
A1: METRICS & CONTROL DEFINITIONS
A2: Use the same definitions in every weekly review. These rules prevent inflated numbers.
A4: Term | B4: Exact meaning | C4: Data entry instructions
A5: Qualified interview | B5: Used 2+ AI coding sessions in one repo within past month, completed interview | C5: Interview Log D = Yes
A6: Recent verified pain | B6: Qualified user describes a real incident in last 30 days | C6: Interview Log E = Yes + sanitized notes
A7: Alpha completion | B7: Finished four-step scenario with no operator takeover | C7: Alpha Testers E = Yes
A8: Verified new install | B8: Distinct new installer confirmed; not downloads or GitHub stars | C8: Weekly Metrics F; deduplicate across weeks
A9: New activation | B9: New user generated a meaningful risk report | C9: Weekly Metrics G; count each user once
A10: New repeat user | B10: Distinct activated user returns in another session/day | C10: Weekly Metrics H; first repeat only
A11: New paying customer | B11: Distinct non-refunded real paying customer | C11: Weekly Metrics I; remove refunded sale from count
A12: Gross USD | B12: Collected sales before fees/refunds | C12: Weekly Metrics J
A13: Net receipts | B13: Gross minus refunds and payment processor fees, not profit | C13: Weekly Metrics J minus K minus L
A14: Critical safety incident | B14: Destructive unapproved change, secret disclosure, or unsafe command execution | C14: Weekly Metrics M; any value >0 blocks rollout
A15: Gate pass | B15: Owner explicitly checks deliverables and evidence | C15: Milestones F = Passed only after review
... A18: Working assumptions | B18: Targets are business validation hypotheses | C18: Revisions must be logged in Decision Log
